jvapi/__init__.py
jvapi/jvapi.py
jvapi/strings.py
jvapi-0.0.5.dist-info/METADATA
jvapi-0.0.5.dist-info/WHEEL
jvapi-0.0.5.dist-info/top_level.txt
jvapi-0.0.5.dist-info/RECORD
